ohmycode/__init__.py
ohmycode/cli.py
ohmycode/core/tools/__Init__.py
ohmycode/core/tools/base.py
ohmycode/core/tools/mypy_tool.py
ohmycode/core/tools/project_tools.py
ohmycode/core/tools/radon_tool.py
ohmycode/core/tools/ruff_tool.py
ohmycode/services/config_service.py
ohmycode/templates/prompt_template.md
ohmycode/templates/report_template.md
ohmycode/utils/config_utils.py
ohmycode/utils/file_utils.py
ohmycode/utils/log_utils.py
ohmycode/utils/prompt_manager.py
ohmycode/utils/report_manager.py
ohmycode/utils/shell_utils.py
ohmycode/utils/formatters/__init__.py
ohmycode/utils/formatters/base.py
ohmycode/utils/formatters/formatter_factory.py
ohmycode/utils/formatters/mypy_formatter.py
ohmycode/utils/formatters/radon_formatter.py
ohmycode/utils/formatters/ruff_formatter.py
ohmycode/web/__init__.py
ohmycode/web/app.py
ohmycode/web/config_types.py
ohmycode/web/api/__init__.py
ohmycode/web/api/config.py
ohmycode/web/api/exclude.py
ohmycode/web/api/history.py
ohmycode/web/config/__init__.py
ohmycode/web/config/manager.py
ohmycode/web/config/mypy_config.py
ohmycode/web/config/radon_config.py
ohmycode/web/config/ruff_config.py
ohmycode/web/config/types.py
ohmycode/web/reports/web_report_manager.py
ohmycode/web/static/index.css
ohmycode/web/static/index.html
ohmycode/web/static/index.js
ohmycode/web/static/vite.svg
ohmycode/web/templates/index.html
ohmycode-0.1.0.3.dist-info/METADATA
ohmycode-0.1.0.3.dist-info/WHEEL
ohmycode-0.1.0.3.dist-info/entry_points.txt
ohmycode-0.1.0.3.dist-info/RECORD
