Metadata-Version: 2.3
Name: ohmycode
Version: 0.1.0.3
Summary: Python项目分析工具
Author-email: Lane <cloudsharein@Gmail.com>
Requires-Dist: aiofiles>=23.2.1
Requires-Dist: click>=8.0.0
Requires-Dist: fastapi>=0.110.0
Requires-Dist: jinja2>=3.1.3
Requires-Dist: mypy>=1.13.0
Requires-Dist: radon>=6.0.1
Requires-Dist: ruff>=0.7.4
Requires-Dist: toml>=0.10.2
Requires-Dist: uvicorn>=0.27.1
